sanic_cors/__init__.py
sanic_cors/core.py
sanic_cors/decorator.py
sanic_cors/extension.py
sanic_cors/version.py
Sanic_Cors-2.1.0.dist-info/LICENSE
Sanic_Cors-2.1.0.dist-info/METADATA
Sanic_Cors-2.1.0.dist-info/WHEEL
Sanic_Cors-2.1.0.dist-info/top_level.txt
Sanic_Cors-2.1.0.dist-info/RECORD
