Metadata-Version: 2.1
Name: Sanic-Cors
Version: 2.1.0
Summary: A Sanic extension adding a decorator for CORS support. Based on flask-cors by Cory Dolphin.
Home-page: https://github.com/ashleysommer/sanic-cors
Author: Ashley Sommer
Author-email: ashleysommer@gmail.com
License: MIT
Platform: any
Classifier: Environment :: Web Environment
Classifier: Intended Audience :: Developers
Classifier: License :: OSI Approved :: MIT License
Classifier: Operating System :: OS Independent
Classifier: Programming Language :: Python
Classifier: Programming Language :: Python :: 3
Classifier: Programming Language :: Python :: 3 :: Only
Classifier: Programming Language :: Python :: 3.7
Classifier: Programming Language :: Python :: 3.8
Classifier: Programming Language :: Python :: 3.9
Classifier: Programming Language :: Python :: 3.10
Classifier: Programming Language :: Python :: Implementation :: CPython
Classifier: Programming Language :: Python :: Implementation :: PyPy
Classifier: Topic :: Internet :: WWW/HTTP :: Dynamic Content
Classifier: Topic :: Software Development :: Libraries :: Python Modules
Requires-Dist: sanic (>=21.9.3)
Requires-Dist: packaging (>=21.3)
